moore_itertools/__init__.py
moore_itertools/product.py
moore_itertools/py.typed
moore_itertools-0.0.3.dist-info/LICENSE.txt
moore_itertools-0.0.3.dist-info/METADATA
moore_itertools-0.0.3.dist-info/WHEEL
moore_itertools-0.0.3.dist-info/top_level.txt
moore_itertools-0.0.3.dist-info/RECORD
